Metadata-Version: 1.1
Name: pyAnalyticsCloud
Version: 0.8.0
Summary: Tools to help load data into Salesforce.com Analytics Cloud
Home-page: https://github.com/heroku/pyAnalyticsCloud
Author: Marc Sibson
Author-email: marc@heroku.com
License: UNKNOWN
Keywords: salesforce,heroku,insights,wave
Platform: UNKNOWN
Classifier: Development Status :: 2 - Pre-Alpha
Classifier: Intended Audience :: Developers
Classifier: License :: OSI Approved :: BSD License
Classifier: Natural Language :: English
Classifier: Programming Language :: Python :: 2
Classifier: Programming Language :: Python :: 2.7
Classifier: Programming Language :: Python :: Implementation :: CPython
Classifier: Programming Language :: Python :: Implementation :: PyPy
